hatTrick/__init__.py
hatTrick/cli.py
hatTrick/decode/HATRX.py
hatTrick/decode/__init__.py
hatTrick/decode/_helpers.py
hatTrick/decode/cli.py
hatTrick/encode/__init__.py
hatTrick/encode/_helpers.py
hatTrick/encode/cli.py
hatTrick/encode/merger.py
hattrick-0.2.1.dist-info/licenses/LICENSE
hattrick-0.2.1.dist-info/METADATA
hattrick-0.2.1.dist-info/WHEEL
hattrick-0.2.1.dist-info/entry_points.txt
hattrick-0.2.1.dist-info/top_level.txt
hattrick-0.2.1.dist-info/RECORD
