Metadata-Version: 2.4
Name: hatTrick
Version: 0.2.1
Summary: Hadamard Transform for Time-Resolved Crystallography
Author-email: Ryan O'Dea <ryan.odea@psi.ch>
Maintainer-email: Ryan O'Dea <ryan.odea@psi.ch>
Keywords: crystallography,SFTRC
Classifier: Development Status :: 3 - Alpha
Classifier: Intended Audience :: Science/Research
Classifier: Topic :: Scientific/Engineering :: Chemistry
Classifier: Topic :: Scientific/Engineering :: Physics
Classifier: License :: OSI Approved :: MIT License
Classifier: Programming Language :: Python :: 3
Classifier: Programming Language :: Python :: 3.8
Classifier: Programming Language :: Python :: 3.9
Classifier: Programming Language :: Python :: 3.10
Classifier: Programming Language :: Python :: 3.11
Classifier: Programming Language :: Python :: 3.12
Requires-Python: >=3.8
License-File: LICENSE
Requires-Dist: numpy>=1.20.0
Requires-Dist: pandas>=1.3.0
Requires-Dist: scipy>=1.7.0
Requires-Dist: click>=8.0.0
Requires-Dist: h5py>=3.0.0
Requires-Dist: bitshuffle>=0.3.0
Dynamic: license-file
